example_pkg/__init__.py
events_ensclient_pypi-0.0.2.dist-info/METADATA
events_ensclient_pypi-0.0.2.dist-info/WHEEL
events_ensclient_pypi-0.0.2.dist-info/top_level.txt
events_ensclient_pypi-0.0.2.dist-info/RECORD
